pfdo_mgz2image/__init__.py
pfdo_mgz2image/__main__.py
pfdo_mgz2image/pfdo_mgz2image.py
pfdo_mgz2image-2.1.8.dist-info/LICENSE
pfdo_mgz2image-2.1.8.dist-info/METADATA
pfdo_mgz2image-2.1.8.dist-info/WHEEL
pfdo_mgz2image-2.1.8.dist-info/entry_points.txt
pfdo_mgz2image-2.1.8.dist-info/top_level.txt
pfdo_mgz2image-2.1.8.dist-info/RECORD
