Metadata-Version: 2.1
Name: pfdo-mgz2image
Version: 2.1.8
Summary: Runs mgz2image on each nested dir of an inputdir
Home-page: http://github.com/FNNDSC/pfdo_mgz2image
Author: FNNDSC
Author-email: dev@babyMRI.org
License: MIT
Requires-Python: >= 3.8
License-File: LICENSE
Requires-Dist: pfmisc
Requires-Dist: pftree
Requires-Dist: pfdo
Requires-Dist: mgz2imgslices ==2.1.3
Requires-Dist: scikit-image
Requires-Dist: nibabel
Requires-Dist: pandas
Requires-Dist: numpy
Requires-Dist: imageio
Requires-Dist: matplotlib
